[
  {
    "pair": "play_music <-> stop_music",
    "total": 171,
    "correct": 129,
    "confused_within_pair": 39,
    "other_error": 3,
    "avg_entropy_correct": 0.3032410395661327,
    "avg_entropy_confused": 2.1972884863530644
  },
  {
    "pair": "alarm_set <-> play_music",
    "total": 105,
    "correct": 88,
    "confused_within_pair": 1,
    "other_error": 16,
    "avg_entropy_correct": 0.28581536300304916,
    "avg_entropy_confused": 1.7407895294410187
  },
  {
    "pair": "play_music <-> weather_query",
    "total": 110,
    "correct": 93,
    "confused_within_pair": 1,
    "other_error": 16,
    "avg_entropy_correct": 0.2935036730598066,
    "avg_entropy_confused": 2.658132566726209
  },
  {
    "pair": "stop_music <-> weather_query",
    "total": 95,
    "correct": 70,
    "confused_within_pair": 1,
    "other_error": 24,
    "avg_entropy_correct": 0.31698677014426513,
    "avg_entropy_confused": 1.5770460600330247
  }
]